invenio_analytics_importer/__init__.py
invenio_analytics_importer/cache.py
invenio_analytics_importer/cli.py
invenio_analytics_importer/config.py
invenio_analytics_importer/convert.py
invenio_analytics_importer/ingest.py
invenio_analytics_importer/read.py
invenio_analytics_importer/retrieve.py
invenio_analytics_importer/write.py
invenio_analytics_importer-0.2.0.dist-info/licenses/LICENSE
invenio_analytics_importer-0.2.0.dist-info/METADATA
invenio_analytics_importer-0.2.0.dist-info/WHEEL
invenio_analytics_importer-0.2.0.dist-info/entry_points.txt
invenio_analytics_importer-0.2.0.dist-info/top_level.txt
invenio_analytics_importer-0.2.0.dist-info/RECORD
