Metadata-Version: 2.4
Name: invenio-analytics-importer
Version: 0.2.0
Summary: Import analytics from 3rd-party provider (Matomo) into InvenioRDM instance.
Author-email: Northwestern University <DL_FSM_GDS@e.northwestern.edu>
License: MIT License
Project-URL: Repository, https://github.com/galterlibrary/invenio-analytics-importer
Keywords: invenio,inveniordm,rdm,analytics,statistics,matomo
Classifier: Environment :: Web Environment
Classifier: Intended Audience :: Developers
Classifier: License :: OSI Approved :: MIT License
Classifier: Operating System :: OS Independent
Classifier: Programming Language :: Python
Classifier: Topic :: Internet :: WWW/HTTP :: Dynamic Content
Classifier: Topic :: Software Development :: Libraries :: Python Modules
Classifier: Programming Language :: Python :: 3
Classifier: Programming Language :: Python :: 3.9
Classifier: Programming Language :: Python :: 3.11
Classifier: Programming Language :: Python :: 3.12
Classifier: Programming Language :: Python :: 3.13
Requires-Python: >=3.9
License-File: LICENSE
Requires-Dist: httpx[cli]>=0.28.1
Requires-Dist: invenio-app-rdm<14.0.0,>=12.0.0
Requires-Dist: click
Requires-Dist: flask
Requires-Dist: invenio_db
Requires-Dist: invenio-rdm-records
Requires-Dist: invenio-search
Requires-Dist: sqlalchemy
Provides-Extra: dev
Requires-Dist: check-manifest>=0.49; extra == "dev"
Requires-Dist: invenio-search[opensearch2]; extra == "dev"
Requires-Dist: invoke<3.0,>=2.2; extra == "dev"
Requires-Dist: pytest-asyncio>=1.2.0; extra == "dev"
Requires-Dist: pytest-invenio>=3.4.2; extra == "dev"
Requires-Dist: time-machine<3.0.0,>=2.12.0; extra == "dev"
Dynamic: license-file
